bulterLibs/__init__.py
bulterLibs/restClient.py
butlerConnect/__init__.py
butlerConnect/pikaButler.py
butlerDescription/__init__.py
butlerDescription/component.py
butlerDescription/control.py
butlerDescription/energyManager.py
butlerDescription/group.py
butlerDescription/signal.py
butler_connect-0.12.14.dist-info/licenses/LICENSE
butler_connect-0.12.14.dist-info/METADATA
butler_connect-0.12.14.dist-info/WHEEL
butler_connect-0.12.14.dist-info/top_level.txt
butler_connect-0.12.14.dist-info/RECORD
