Metadata-Version: 2.4
Name: butler-connect
Version: 0.12.14
Summary: Access libraries (with pika) and data definitions for the Buttler project.
Author-email: Oliver Birkholz <info@aibutler.de>
License-Expression: MIT
Keywords: feed,reader,tutorial
Classifier: Programming Language :: Python
Classifier: Programming Language :: Python :: 3
Requires-Python: >=3.7
License-File: LICENSE
Requires-Dist: sseclient
Requires-Dist: requests
Requires-Dist: pika
Requires-Dist: marshmallow
Provides-Extra: dev
Requires-Dist: black; extra == "dev"
Requires-Dist: bumpver; extra == "dev"
Requires-Dist: isort; extra == "dev"
Requires-Dist: pip-tools; extra == "dev"
Requires-Dist: pytest; extra == "dev"
Dynamic: license-file
